flask_staticify
