Metadata-Version: 1.1
Name: Flask-Staticify
Version: 0.2.1
Summary: Looks for static files in the additional locations as a fallback
Home-page: https://github.com/mstolyarchuk/flask-staticify
Author: Maxim Stolyarchuk
Author-email: maxim.stolyarchuk@gmail.com
License: BSD
Platform: any
Classifier: Environment :: Web Environment
Classifier: Intended Audience :: Developers
Classifier: License :: OSI Approved :: BSD License
Classifier: Operating System :: OS Independent
Classifier: Programming Language :: Python
Classifier: Topic :: Internet :: WWW/HTTP :: Dynamic Content
Classifier: Topic :: Software Development :: Libraries :: Python Modules
